{
  "url": "https://micekart.com/mice-packages/Kazakhstan/corportetourpackagealmaty/NzU=",
  "status_code": 200,
  "title": "Almaty - MICE Packages - MICEkart - MICE Packages - MICEkart",
  "description": "MICEkart.com offers you fully managed corporate tour packages and tailor-made business travel solutions for your Incentive Trips and Corporate Events. Get in Touch +919167499292",
  "keywords": "Almaty,Almaty - MICEkart,MICE travel Almaty,Corporate Travel Packages Almaty,Incentive Trips Almaty,Group Tour Packages Almaty",
  "detected_interactive_elements": [
    "infinite_scroll"
  ],
  "has_javascript": true,
  "extraction_method": "interactive_crawl4ai",
  "success": true,
  "content_length": 18938
}